dagfactory/__init__.py
dagfactory/__version__.py
dagfactory/dagbuilder.py
dagfactory/dagfactory.py
dagfactory/utils.py
dag_factory_hotfix-0.11.1.dist-info/LICENSE
dag_factory_hotfix-0.11.1.dist-info/METADATA
dag_factory_hotfix-0.11.1.dist-info/WHEEL
dag_factory_hotfix-0.11.1.dist-info/top_level.txt
dag_factory_hotfix-0.11.1.dist-info/RECORD
