Metadata-Version: 2.1
Name: dag-factory-hotfix
Version: 0.11.1
Summary: Dynamically build Airflow DAGs from YAML files
Home-page: https://github.com/ajbosco/dag-factory
Author: Adam Boscarino
Author-email: adam@boscarino.me
License: MIT
Keywords: airflow
Platform: UNKNOWN
Classifier: License :: OSI Approved :: MIT License
Classifier: Programming Language :: Python
Classifier: Programming Language :: Python :: 3
Classifier: Programming Language :: Python :: 3.6
Classifier: Programming Language :: Python :: Implementation :: CPython
Classifier: Programming Language :: Python :: Implementation :: PyPy
Requires-Python: >=3.6.0
Requires-Dist: apache-airflow[http,kubernetes] (>=1.10.0)
Requires-Dist: pyyaml
Requires-Dist: packaging
Provides-Extra: dev
Requires-Dist: black ; extra == 'dev'
Requires-Dist: pytest ; extra == 'dev'
Requires-Dist: pylint ; extra == 'dev'
Requires-Dist: pytest-cov ; extra == 'dev'
Requires-Dist: tox ; extra == 'dev'
